{
  "designerVersion" : "1.9.24",
  "previousDesignerVersion" : "1.7.25",
  "id" : "layout90sBis",
  "name" : "layout90sBis",
  "lastUpdate" : 1557420735842,
  "rows" : [ [ {
    "type" : "container",
    "dimension" : {
      "xs" : 12,
      "sm" : 12,
      "md" : 12,
      "lg" : 12
    },
    "propertyValues" : {
      "cssClasses" : {
        "type" : "constant",
        "value" : "layout-header"
      },
      "hidden" : {
        "type" : "constant",
        "value" : false
      },
      "repeatedCollection" : {
        "type" : "variable",
        "value" : ""
      }
    },
    "reference" : "2a42e7c9-c7a6-4f7c-9826-2c24c8b311f9",
    "hasValidationError" : false,
    "id" : "pbContainer",
    "rows" : [ [ {
      "type" : "container",
      "dimension" : {
        "xs" : 12,
        "sm" : 12,
        "md" : 12,
        "lg" : 12
      },
      "propertyValues" : {
        "cssClasses" : {
          "type" : "constant",
          "value" : ""
        },
        "hidden" : {
          "type" : "constant",
          "value" : false
        },
        "repeatedCollection" : {
          "type" : "variable",
          "value" : ""
        }
      },
      "reference" : "e844b04b-6a71-43d2-a301-3f4c1e522c4e",
      "hasValidationError" : false,
      "id" : "pbContainer",
      "rows" : [ [ {
        "type" : "component",
        "dimension" : {
          "xs" : 12,
          "sm" : 12,
          "md" : 12,
          "lg" : 12
        },
        "propertyValues" : {
          "cssClasses" : {
            "type" : "constant",
            "value" : ""
          },
          "hidden" : {
            "type" : "constant",
            "value" : false
          },
          "allowHTML" : {
            "type" : "constant",
            "value" : true
          },
          "text" : {
            "type" : "interpolation",
            "value" : "<br/>\n<br/>\n<br/>\n<p class=\"colorTitle\">⏰ BONITASOFT ESCAPE GAME - INSCRIPTIONS ⏰</p>\n<br/>\n<br/>\n<br/>"
          },
          "alignment" : {
            "type" : "constant",
            "value" : "center"
          },
          "labelHidden" : {
            "type" : "constant",
            "value" : true
          },
          "label" : {
            "type" : "interpolation",
            "value" : ""
          },
          "labelPosition" : {
            "type" : "constant",
            "value" : "top"
          },
          "labelWidth" : {
            "type" : "constant",
            "value" : 4
          }
        },
        "reference" : "83d4952d-e96b-4edf-9ed8-3938f24e9789",
        "hasValidationError" : false,
        "id" : "pbText"
      } ] ]
    } ], [ {
      "type" : "component",
      "dimension" : {
        "xs" : 12,
        "sm" : 12,
        "md" : 12,
        "lg" : 12
      },
      "propertyValues" : {
        "cssClasses" : {
          "type" : "constant",
          "value" : ""
        },
        "hidden" : {
          "type" : "constant",
          "value" : true
        },
        "targetUrl" : {
          "type" : "variable",
          "value" : "targetedPageUrl"
        }
      },
      "reference" : "ff3ccd8d-bca9-4e2c-9a60-e37fbbc8692b",
      "hasValidationError" : false,
      "id" : "customLivingApplicationMenuV4"
    } ] ]
  } ], [ {
    "type" : "container",
    "dimension" : {
      "xs" : 12,
      "sm" : 12,
      "md" : 12,
      "lg" : 12
    },
    "propertyValues" : {
      "cssClasses" : {
        "type" : "constant",
        "value" : "layout-content"
      },
      "hidden" : {
        "type" : "constant",
        "value" : false
      },
      "repeatedCollection" : {
        "type" : "variable",
        "value" : ""
      }
    },
    "reference" : "c9ecf66c-c5a2-47ea-8bdc-c89c55337027",
    "hasValidationError" : false,
    "id" : "pbContainer",
    "rows" : [ [ {
      "type" : "component",
      "dimension" : {
        "xs" : 12,
        "sm" : 12,
        "md" : 12,
        "lg" : 12
      },
      "propertyValues" : {
        "cssClasses" : {
          "type" : "constant",
          "value" : ""
        },
        "hidden" : {
          "type" : "constant",
          "value" : false
        },
        "src" : {
          "type" : "variable",
          "value" : "targetedPageUrl"
        }
      },
      "reference" : "ce8d04a0-db06-462a-a0d5-d56ab6cbf527",
      "hasValidationError" : false,
      "id" : "customLivingApplicationIFrameV4"
    } ] ]
  } ], [ {
    "type" : "container",
    "dimension" : {
      "xs" : 12,
      "sm" : 12,
      "md" : 12,
      "lg" : 12
    },
    "propertyValues" : {
      "cssClasses" : {
        "type" : "constant",
        "value" : "layout-footer"
      },
      "hidden" : {
        "type" : "constant",
        "value" : false
      },
      "repeatedCollection" : {
        "type" : "variable",
        "value" : ""
      }
    },
    "reference" : "c789b4a6-7dd3-4917-97cf-c7b792d98484",
    "hasValidationError" : false,
    "id" : "pbContainer",
    "rows" : [ [ {
      "type" : "component",
      "dimension" : {
        "xs" : 12,
        "sm" : 12,
        "md" : 12,
        "lg" : 12
      },
      "propertyValues" : {
        "cssClasses" : {
          "type" : "constant",
          "value" : ""
        },
        "hidden" : {
          "type" : "constant",
          "value" : false
        },
        "allowHTML" : {
          "type" : "constant",
          "value" : true
        },
        "text" : {
          "type" : "interpolation",
          "value" : "<p class=\"h3\">Powered by</p>"
        },
        "alignment" : {
          "type" : "constant",
          "value" : "center"
        },
        "labelHidden" : {
          "type" : "constant",
          "value" : true
        },
        "label" : {
          "type" : "interpolation",
          "value" : ""
        },
        "labelPosition" : {
          "type" : "constant",
          "value" : "top"
        },
        "labelWidth" : {
          "type" : "constant",
          "value" : 4
        }
      },
      "reference" : "2557ace7-99e6-4626-acc5-82b601fcc686",
      "hasValidationError" : false,
      "id" : "pbText"
    } ], [ {
      "type" : "container",
      "dimension" : {
        "xs" : 12,
        "sm" : 12,
        "md" : 4,
        "lg" : 5
      },
      "propertyValues" : {
        "cssClasses" : {
          "type" : "constant",
          "value" : ""
        },
        "hidden" : {
          "type" : "constant",
          "value" : false
        },
        "repeatedCollection" : {
          "type" : "variable",
          "value" : ""
        }
      },
      "reference" : "ebf6e7a7-0bdc-458d-a175-4fbbbb06591b",
      "hasValidationError" : false,
      "id" : "pbContainer",
      "rows" : [ [ ] ]
    }, {
      "type" : "component",
      "dimension" : {
        "xs" : 12,
        "sm" : 12,
        "md" : 4,
        "lg" : 4
      },
      "propertyValues" : {
        "cssClasses" : {
          "type" : "constant",
          "value" : ""
        },
        "hidden" : {
          "type" : "constant",
          "value" : false
        },
        "srcType" : {
          "type" : "constant",
          "value" : "Asset"
        },
        "url" : {
          "type" : "constant"
        },
        "assetName" : {
          "type" : "constant",
          "value" : "logoRouge.png"
        },
        "alt" : {
          "type" : "interpolation"
        }
      },
      "reference" : "c89cc3eb-3fa1-419b-a2cf-1e4cfd90cae7",
      "hasValidationError" : false,
      "id" : "pbImage"
    }, {
      "type" : "container",
      "dimension" : {
        "xs" : 12,
        "sm" : 12,
        "md" : 4,
        "lg" : 3
      },
      "propertyValues" : {
        "cssClasses" : {
          "type" : "constant",
          "value" : ""
        },
        "hidden" : {
          "type" : "constant",
          "value" : false
        },
        "repeatedCollection" : {
          "type" : "variable",
          "value" : ""
        }
      },
      "reference" : "4e5ca8b0-1c75-40e8-b6f4-76a73c8b4c66",
      "hasValidationError" : false,
      "id" : "pbContainer",
      "rows" : [ [ ] ]
    } ] ]
  } ], [ {
    "type" : "component",
    "dimension" : {
      "xs" : 12,
      "sm" : 12,
      "md" : 12,
      "lg" : 12
    },
    "propertyValues" : {
      "cssClasses" : {
        "type" : "constant",
        "value" : ""
      },
      "hidden" : {
        "type" : "constant",
        "value" : true
      },
      "type" : {
        "type" : "constant",
        "value" : "URL"
      },
      "url" : {
        "type" : "constant",
        "value" : ""
      },
      "document" : {
        "type" : "variable",
        "value" : ""
      },
      "showPreview" : {
        "type" : "constant",
        "value" : false
      }
    },
    "reference" : "7bc91559-be60-4087-9189-d73e85a1b06e",
    "hasValidationError" : false,
    "id" : "pbFileViewer"
  } ] ],
  "assets" : [ {
    "id" : "5183f0fd-6bf3-467c-a2c0-2c13dc332e9c",
    "name" : "animation386.js",
    "type" : "js",
    "order" : 9,
    "external" : false
  }, {
    "id" : "e9512b72-26da-4646-ae30-a32f4a362f0f",
    "name" : "bootstrap.css",
    "type" : "css",
    "order" : 2,
    "external" : false
  }, {
    "id" : "ae6f3487-98cd-4920-9e5a-ff61c324e5a4",
    "name" : "bootstrap-theme.css",
    "type" : "css",
    "order" : 3,
    "external" : false
  }, {
    "id" : "2007621b-afa8-48ec-846f-f4d78ce90b8a",
    "name" : "layout.css",
    "type" : "css",
    "order" : 1,
    "external" : false
  }, {
    "id" : "2a2ac6a1-2895-4a40-a639-f97d21a11de1",
    "name" : "logo.png",
    "type" : "img",
    "order" : 16,
    "external" : false
  }, {
    "id" : "9300e21b-5209-4e62-b1c5-f208af822434",
    "name" : "Fixedsys500c.otf",
    "type" : "css",
    "order" : 11,
    "external" : false
  }, {
    "id" : "4d4aa1e1-b69b-4600-8300-3732ee5eb9e1",
    "name" : "Fixedsys500c.svg",
    "type" : "css",
    "order" : 12,
    "external" : false
  }, {
    "id" : "8600b059-e2a0-4fc6-a35c-aa026d52c45a",
    "name" : "logoRouge.png",
    "type" : "img",
    "order" : 17,
    "external" : false
  }, {
    "id" : "da2ff6d7-72e0-4ec1-9c5a-7372b83cdc7a",
    "name" : "Fixedsys500c.ttf",
    "type" : "css",
    "order" : 13,
    "external" : false
  }, {
    "id" : "96e7d863-f4f5-4839-9026-1d9bdd8e4853",
    "name" : "Fixedsys500c.eot",
    "type" : "css",
    "order" : 10,
    "external" : false
  }, {
    "id" : "616b59a4-9c06-4c86-924d-0d076ee131c4",
    "name" : "bootstrap.js",
    "type" : "js",
    "order" : 15,
    "external" : false
  }, {
    "id" : "27b2007f-d336-4f20-b640-5810f7a8af54",
    "name" : "layout.js",
    "type" : "js",
    "order" : 0,
    "external" : false
  }, {
    "id" : "32cfafe9-d36d-4e1a-95b0-f4281c96de6e",
    "name" : "Fixedsys500c.woff",
    "type" : "css",
    "order" : 14,
    "external" : false
  } ],
  "inactiveAssets" : [ ],
  "data" : {
    "targetedPageUrl" : {
      "type" : "constant",
      "value" : "../../../portal/resource/app/escpaeGameApps/classement/content/?_l=en&app=escpaeGameApps",
      "exposed" : false
    }
  },
  "hasValidationError" : false,
  "uuid" : "221d2b2d-54dd-4ca5-adc8-af9e8619f0c9",
  "type" : "layout",
  "description" : "Page generated with Bonita UI designer"
}